nc2gj/__init__.py
nc2gj/cmems_datasets.py
nc2gj/nc2geojson.py
nc2gj/version.py
nc2gj-0.0.16.dist-info/LICENCE
nc2gj-0.0.16.dist-info/METADATA
nc2gj-0.0.16.dist-info/WHEEL
nc2gj-0.0.16.dist-info/entry_points.txt
nc2gj-0.0.16.dist-info/top_level.txt
nc2gj-0.0.16.dist-info/RECORD
