Metadata-Version: 2.1
Name: nc2gj
Version: 0.0.16
Home-page: https://gitlab.mercator-ocean.fr/mirazoki/ecfas_geojason
Author: Maialen Irazoki
Author-email: mirazoki@mercator-ocean.fr
License: BSD Licence
Project-URL: Repository, https://gitlab.mercator-ocean.fr/mirazoki/ecfas_geojason
Classifier: Development Status :: 4 - Beta
Classifier: Intended Audience :: Science/Research
Classifier: Topic :: Scientific/Engineering
Classifier: Environment :: Console
Classifier: Programming Language :: Python :: 3.10
Classifier: License :: OSI Approved :: BSD License
Requires-Python: >=3.10
License-File: LICENCE
Requires-Dist: xarray (==2022.3.0)
Requires-Dist: netcdf4 (==1.5.8)
